readsql/__init__.py
readsql/__main__.py
readsql/regexes.txt
readsql-1.1.0.dist-info/METADATA
readsql-1.1.0.dist-info/WHEEL
readsql-1.1.0.dist-info/entry_points.txt
readsql-1.1.0.dist-info/licenses/LICENSE
readsql-1.1.0.dist-info/RECORD
