Metadata-Version: 2.4
Name: readsql
Version: 1.1.0
Summary: Convert SQL to most human readable format
Project-URL: Repository, https://github.com/AzisK/readsql/
Author-email: Azis <azuolas.krusna@yahoo.com>
Maintainer-email: Azis <azuolas.krusna@yahoo.com>
License-Expression: MIT
License-File: LICENSE
Keywords: Lint,Python,SQL
Requires-Python: >=3.8
Provides-Extra: dev
Requires-Dist: pytest>=7.0; extra == 'dev'
